safetensors-0.6.1.dist-info/METADATA
safetensors-0.6.1.dist-info/WHEEL
safetensors-0.6.1.dist-info/licenses/LICENSE
safetensors/__init__.py
safetensors/__init__.pyi
safetensors/_safetensors_rust.abi3.so
safetensors/flax.py
safetensors/mlx.py
safetensors/numpy.py
safetensors/paddle.py
safetensors/py.typed
safetensors/tensorflow.py
safetensors/torch.py
safetensors-0.6.1.dist-info/RECORD
